zaide/__cls_aide_base__.py
zaide/__cls_aide_rst__.py
zaide/__cls_aide_rst_files__.py
zaide/__init__.py
zaide-4.3.dist-info/LICENSE
zaide-4.3.dist-info/METADATA
zaide-4.3.dist-info/WHEEL
zaide-4.3.dist-info/top_level.txt
zaide-4.3.dist-info/RECORD
