Metadata-Version: 2.1
Name: zaide
Version: 4.3
Summary: A useless model
Home-page: https://github.com/zhstack/zaide.git
Author: zhstack
Author-email: zhstack@163.com
License: MIT
Keywords: zaide
License-File: LICENSE
